django_descope/__init__.py
django_descope/apps.py
django_descope/authentication.py
django_descope/conf.py
django_descope/middleware.py
django_descope/migrations/0001_initial.py
django_descope/migrations/__init__.py
django_descope/models.py
django_descope/templates/admin/descope_login.html
django_descope/templatetags/__init__.py
django_descope/templatetags/descope.py
django_descope/test_store_jwt.py
django_descope/urls.py
django_descope/views.py
django_descope-2.1.0.dist-info/LICENSE
django_descope-2.1.0.dist-info/METADATA
django_descope-2.1.0.dist-info/WHEEL
django_descope-2.1.0.dist-info/RECORD
